PsyeonTest/test1.py
PsyeonTest/test2.py
PsyeonTest-0.0.0.2.dist-info/METADATA
PsyeonTest-0.0.0.2.dist-info/WHEEL
PsyeonTest-0.0.0.2.dist-info/top_level.txt
PsyeonTest-0.0.0.2.dist-info/RECORD
