Metadata-Version: 2.1
Name: PsyeonTest
Version: 0.0.0.2
Summary: My First Test Package
Home-page: https://blog.naver.com/hulcheongi
Author: Seungyeon Park
Author-email: lingua72@gmail.com
License: MIT
Platform: UNKNOWN
Requires-Python: >=3
